egnyte/exc.py
egnyte/base.py
egnyte/audits.py
egnyte/__init__.py
egnyte/resources.py
egnyte/configuration.py
egnyte/__main__.py
egnyte/events.py
egnyte/client.py
egnyte/tests/helpers.py
egnyte/tests/test_links.py
egnyte/tests/test_files.py
egnyte/tests/test_audits.py
egnyte/tests/test_comments.py
egnyte/tests/test_settings.py
egnyte/tests/test_users.py
egnyte/tests/test_events.py
egnyte/tests/__init__.py
egnyte/tests/test_search.py
egnyte/tests/test_groups.py
egnyte/tests/config.py
egnyte/tests/test_permissions.py
egnyte/tests/test_folders.py
egnyte-0.5.3.dist-info/WHEEL
egnyte-0.5.3.dist-info/metadata.json
egnyte-0.5.3.dist-info/RECORD
egnyte-0.5.3.dist-info/DESCRIPTION.rst
egnyte-0.5.3.dist-info/METADATA
egnyte-0.5.3.dist-info/top_level.txt
egnyte-0.5.3.dist-info/zip-safe
