Metadata-Version: 2.0
Name: egnyte
Version: 0.5.3
Summary: Egnyte Public API SDK
Home-page: https://developers.egnyte.com/
Author: Egnyte
Author-email: api-support@egnyte.com
License: MIT
Platform: Any
Classifier: Programming Language :: Python :: 2.7
Classifier: Programming Language :: Python :: 3.3
Classifier: Programming Language :: Python :: 3.4
Classifier: Development Status :: 4 - Beta
Classifier: Intended Audience :: Developers
Classifier: License :: OSI Approved :: MIT License
Classifier: Operating System :: OS Independent
Classifier: Topic :: Software Development :: Libraries :: Python Modules
Requires-Dist: requests (>=2.13.0)
Requires-Dist: six (>=1.10.0)
Provides-Extra: docs
Requires-Dist: sphinx; extra == 'docs'
Requires-Dist: sphinx-argparse; extra == 'docs'
